odoo/addons/account_bank_statement_import_adyen/README.rst
odoo/addons/account_bank_statement_import_adyen/__init__.py
odoo/addons/account_bank_statement_import_adyen/__manifest__.py
odoo/addons/account_bank_statement_import_adyen/i18n/account_bank_statement_import_adyen.pot
odoo/addons/account_bank_statement_import_adyen/models/__init__.py
odoo/addons/account_bank_statement_import_adyen/models/account_bank_statement_import.py
odoo/addons/account_bank_statement_import_adyen/models/account_bank_statement_import_adyen_parser.py
odoo/addons/account_bank_statement_import_adyen/models/account_journal.py
odoo/addons/account_bank_statement_import_adyen/readme/CONFIGURE.rst
odoo/addons/account_bank_statement_import_adyen/readme/CONTRIBUTORS.rst
odoo/addons/account_bank_statement_import_adyen/readme/DESCRIPTION.rst
odoo/addons/account_bank_statement_import_adyen/readme/USAGE.rst
odoo/addons/account_bank_statement_import_adyen/static/description/icon.png
odoo/addons/account_bank_statement_import_adyen/static/description/index.html
odoo/addons/account_bank_statement_import_adyen/test_files/adyen_test.xlsx
odoo/addons/account_bank_statement_import_adyen/test_files/adyen_test_credit_fees.xlsx
odoo/addons/account_bank_statement_import_adyen/test_files/adyen_test_invalid.xls
odoo/addons/account_bank_statement_import_adyen/test_files/settlement_detail_report_batch_238.csv
odoo/addons/account_bank_statement_import_adyen/test_files/settlement_detail_report_batch_380.csv
odoo/addons/account_bank_statement_import_adyen/tests/__init__.py
odoo/addons/account_bank_statement_import_adyen/tests/test_import_adyen.py
odoo/addons/account_bank_statement_import_adyen/views/account_journal.xml
odoo13_addon_account_bank_statement_import_adyen-13.0.1.0.1.dev11.dist-info/METADATA
odoo13_addon_account_bank_statement_import_adyen-13.0.1.0.1.dev11.dist-info/WHEEL
odoo13_addon_account_bank_statement_import_adyen-13.0.1.0.1.dev11.dist-info/top_level.txt
odoo13_addon_account_bank_statement_import_adyen-13.0.1.0.1.dev11.dist-info/RECORD
